chat_tools/__init__.py
chat_tools/chatgpt.py
chat_tools/commands.py
chat_tools/deepseek.py
chat_tools/gemini.py
chat_tools/groq.py
chat_tools/mistral.py
chat_tools/mixin.py
chat_tools/ollama.py
chat_tools/utils.py
chat_tools-2.3.dist-info/licenses/LICENSE
chat_tools-2.3.dist-info/METADATA
chat_tools-2.3.dist-info/WHEEL
chat_tools-2.3.dist-info/top_level.txt
chat_tools-2.3.dist-info/RECORD
