Metadata-Version: 2.4
Name: chat-tools
Version: 2.3
Summary: Tools for human-machine interaction based on large language models.
Author-email: William Song <30965609+Freakwill@users.noreply.github.com>
License-Expression: MIT
Project-URL: Homepage, https://github.com/Freakwill/chat-tools
Project-URL: Repository, https://github.com/Freakwill/chat-tools
Keywords: Large Language Models,Artificial Intelligence,DeepSeek,Genimi,OpenAI
Classifier: Environment :: MacOS X
Classifier: Programming Language :: Python :: 3
Classifier: Operating System :: OS Independent
Classifier: Development Status :: 5 - Production/Stable
Classifier: Natural Language :: English
Classifier: Programming Language :: Python :: 3.10
Classifier: Programming Language :: Python :: 3.11
Classifier: Programming Language :: Python :: 3.12
Classifier: Topic :: Scientific/Engineering :: Artificial Intelligence
Classifier: Topic :: Software Development :: Libraries :: Python Modules
Classifier: Intended Audience :: Science/Research
Classifier: Intended Audience :: Developers
Requires-Python: >=3.10
License-File: LICENSE
Requires-Dist: openai
Dynamic: license-file
